<?xml version="1.0" encoding="utf-8"?> 
<result> 
 <err_code>
  000
 </err_code> 
 <err_msg>
  정상
 </err_msg> 
 <crp_nm>
  (주)바이오인프라생명과학
 </crp_nm> 
 <crp_nm_e>
  BioInfra Life Science Inc.
 </crp_nm_e> 
 <crp_nm_i>
  바이오인프라생명과학
 </crp_nm_i> 
 <stock_cd></stock_cd> 
 <ceo_nm>
  김철우
 </ceo_nm> 
 <crp_cls>
  E
 </crp_cls> 
 <crp_no>
  1246110241808
 </crp_no> 
 <bsn_no>
  1218142247
 </bsn_no> 
 <adr>
  서울특별시 종로구 대학로 49 (연건동) SGI빌딩 7층
 </adr> 
 <hm_url>
  www.bioinfra.co.kr
 </hm_url> 
 <ir_url></ir_url> 
 <phn_no>
  02-6271-0102
 </phn_no> 
 <fax_no>
  02-6499-1941
 </fax_no> 
 <ind_cd>
  70113
 </ind_cd> 
 <est_dt>
  20010130
 </est_dt> 
 <acc_mt>
  12
 </acc_mt> 
</result>