<?xml version="1.0" encoding="utf-8"?> 
<result> 
 <err_code>
  000
 </err_code> 
 <err_msg>
  정상
 </err_msg> 
 <crp_nm>
  (주)새로닉스
 </crp_nm> 
 <crp_nm_e>
  SERONICS. CO., LTD.
 </crp_nm_e> 
 <crp_nm_i>
  새로닉스
 </crp_nm_i> 
 <stock_cd>
  042600
 </stock_cd> 
 <ceo_nm>
  허제홍
 </ceo_nm> 
 <crp_cls>
  K
 </crp_cls> 
 <crp_no>
  1753110000762
 </crp_no> 
 <bsn_no>
  5138101294
 </bsn_no> 
 <adr>
  경상북도 구미시 수출대로9길 36 (주)새로닉스
 </adr> 
 <hm_url>
  www.seronics.co.kr
 </hm_url> 
 <ir_url></ir_url> 
 <phn_no>
  054-463-7945
 </phn_no> 
 <fax_no>
  054-461-0754
 </fax_no> 
 <ind_cd>
  2629
 </ind_cd> 
 <est_dt>
  19681221
 </est_dt> 
 <acc_mt>
  12
 </acc_mt> 
</result>