<?xml version="1.0" encoding="utf-8"?> 
<result> 
 <err_code>
  000
 </err_code> 
 <err_msg>
  정상
 </err_msg> 
 <crp_nm>
  (주)안지오랩
 </crp_nm> 
 <crp_nm_e>
  AngioLab, Inc.
 </crp_nm_e> 
 <crp_nm_i>
  안지오랩
 </crp_nm_i> 
 <stock_cd>
  251280
 </stock_cd> 
 <ceo_nm>
  김민영
 </ceo_nm> 
 <crp_cls>
  N
 </crp_cls> 
 <crp_no>
  1601110082795
 </crp_no> 
 <bsn_no>
  3148126271
 </bsn_no> 
 <adr>
  대전광역시 유성구 테크노3로 65
 </adr> 
 <hm_url>
  www.angiolab.co.kr
 </hm_url> 
 <ir_url></ir_url> 
 <phn_no>
  042-867-5785
 </phn_no> 
 <fax_no>
  042-867-5787
 </fax_no> 
 <ind_cd>
  70113
 </ind_cd> 
 <est_dt>
  19990615
 </est_dt> 
 <acc_mt>
  12
 </acc_mt> 
</result>