<?xml version="1.0" encoding="utf-8"?> 
<result> 
 <err_code>
  000
 </err_code> 
 <err_msg>
  정상
 </err_msg> 
 <crp_nm>
  영화테크(주)
 </crp_nm> 
 <crp_nm_e>
  Younghwa Tech Co., Ltd.
 </crp_nm_e> 
 <crp_nm_i>
  영화테크
 </crp_nm_i> 
 <stock_cd>
  265560
 </stock_cd> 
 <ceo_nm>
  엄준형
 </ceo_nm> 
 <crp_cls>
  K
 </crp_cls> 
 <crp_no>
  1615110038129
 </crp_no> 
 <bsn_no>
  3128143672
 </bsn_no> 
 <adr>
  충청남도 아산시 둔포면 아산밸리로 132
 </adr> 
 <hm_url>
  www.yhtec.com
 </hm_url> 
 <ir_url></ir_url> 
 <phn_no>
  041-585-2685
 </phn_no> 
 <fax_no></fax_no> 
 <ind_cd>
  3033
 </ind_cd> 
 <est_dt>
  20000808
 </est_dt> 
 <acc_mt>
  12
 </acc_mt> 
</result>