<?xml version="1.0" encoding="utf-8"?> 
<result> 
 <err_code>
  000
 </err_code> 
 <err_msg>
  정상
 </err_msg> 
 <crp_nm>
  디에스씨인베스트먼트(주)
 </crp_nm> 
 <crp_nm_e>
  DSC Investment Inc.
 </crp_nm_e> 
 <crp_nm_i>
  DSC인베스트먼트
 </crp_nm_i> 
 <stock_cd>
  241520
 </stock_cd> 
 <ceo_nm>
  윤건수
 </ceo_nm> 
 <crp_cls>
  K
 </crp_cls> 
 <crp_no>
  1101114778267
 </crp_no> 
 <bsn_no>
  2208831804
 </bsn_no> 
 <adr>
  서울특별시 성동구 뚝섬로1길 10 (성수동1가) 3층
 </adr> 
 <hm_url>
  www.dscinvestment.com
 </hm_url> 
 <ir_url></ir_url> 
 <phn_no>
  02-3453-3190
 </phn_no> 
 <fax_no>
  02-3453-3189
 </fax_no> 
 <ind_cd>
  64209
 </ind_cd> 
 <est_dt>
  20120118
 </est_dt> 
 <acc_mt>
  12
 </acc_mt> 
</result>